gitbrowserinteract/Hardcoded.py
gitbrowserinteract/Website_controller.py
gitbrowserinteract/__init__.py
gitbrowserinteract/__main__.py
gitbrowserinteract/ask_user_input.py
gitbrowserinteract/check_if_firefox_is_installed.py
gitbrowserinteract/control_website.py
gitbrowserinteract/export_token.py
gitbrowserinteract/helper.py
gitbrowserinteract/GitHub/Github_personal_access_token_getter.py
gitbrowserinteract/GitHub/Ssh_deploy_key_setter.py
gitbrowserinteract/GitHub/__init__.py
gitbrowserinteract/GitHub/github_login.py
gitbrowserinteract/GitHub/remove_previous_github_pat.py
gitbrowserinteract/GitHub/remove_previous_github_ssh_key.py
gitbrowserinteract/GitLab/GitLab_runner_token_getter.py
gitbrowserinteract/GitLab/__init__.py
gitbrowserinteract/GitLab/get_gitlab_runner_token.py
gitbrowserinteract/GitLab/login_gitlab.py
gitbrowserinteract-0.0.9.dist-info/METADATA
gitbrowserinteract-0.0.9.dist-info/WHEEL
gitbrowserinteract-0.0.9.dist-info/entry_points.txt
gitbrowserinteract-0.0.9.dist-info/top_level.txt
gitbrowserinteract-0.0.9.dist-info/RECORD
